LICENSE
MANIFEST.in
README.rst
setup.py
req_base/__init__.py
req_base/admin.py
req_base/apps.py
req_base/models.py
req_base/tests.py
req_base/views.py
req_base/migrations/__init__.py
sa_zad_req_base/__init__.py
sa_zad_req_base/base_exceptions.py
sa_zad_req_base/codes.py
sa_zad_req_base/request_base.py
sa_zad_req_base/settings.py
sa_zad_req_base/urls.py
sa_zad_req_base/utils.py
sa_zad_req_base/wsgi.py
sa_zad_req_base.egg-info/PKG-INFO
sa_zad_req_base.egg-info/SOURCES.txt
sa_zad_req_base.egg-info/dependency_links.txt
sa_zad_req_base.egg-info/top_level.txt